PyMMB/__init__.py
PyMMB/_version.py
PyMMB/bcd.py
PyMMB/dfs.py
PyMMB/mmb.py
pymmb-1.0.0.dist-info/COPYING
pymmb-1.0.0.dist-info/METADATA
pymmb-1.0.0.dist-info/WHEEL
pymmb-1.0.0.dist-info/top_level.txt
pymmb-1.0.0.dist-info/RECORD
