Metadata-Version: 2.1
Name: pymmb
Version: 1.0.0
Summary: Python library for accessing BBC Microcomputer DFS disk images and MMB disk bundles
Home-page: https://projects.limbicly.com/bbc-micro/PyMMB
Author: Adrian Hungate
Author-email: adrian@limbicly.com
License: UNKNOWN
Platform: UNKNOWN
Classifier: Development Status :: 5 - Production/Stable
Classifier: Intended Audience :: End Users/Desktop
Classifier: License :: OSI Approved :: Apache Software License
Classifier: Natural Language :: English
Classifier: Operating System :: OS Independent
Classifier: Programming Language :: Python
Classifier: Programming Language :: Python :: 2
Classifier: Topic :: System :: Filesystems
Classifier: Topic :: Utilities
Requires-Python: >=2.5, <3
